Uart/Alejandro/rtl/uart/uart.v
//-----------------------------------------------------
// Design Name : uart 
// File Name   : uart.v
// Function    : Simple UART
// Coder       : Deepak Kumar Tala
//-----------------------------------------------------
module uart (
reset          ,
txclk          ,
ld_tx_data     ,
tx_data        ,
tx_enable      ,
tx_out         ,
tx_empty       ,
rxclk          ,
uld_rx_data    ,
rx_data        ,
rx_enable      ,
rx_in          ,
rx_empty
);
// Port declarations
input        reset          ;
input        txclk          ;
input        ld_tx_data     ;
input  [7:0] tx_data        ;
input        tx_enable      ;
output       tx_out         ;
output       tx_empty       ;
input        rxclk          ;
input        uld_rx_data    ;
output [7:0] rx_data        ;
input        rx_enable      ;
input        rx_in          ;
output       rx_empty       ;

// Internal Variables 
reg [7:0]    tx_reg         ;
reg          tx_empty       ;
reg          tx_over_run    ;
reg [3:0]    tx_cnt         ;
reg          tx_out         ;
reg [7:0]    rx_reg         ;
reg [7:0]    rx_data        ;
reg [3:0]    rx_sample_cnt  ;
reg [3:0]    rx_cnt         ;  
reg          rx_frame_err   ;
reg          rx_over_run    ;
reg          rx_empty       ;
reg          rx_d1          ;
reg          rx_d2          ;
reg          rx_busy        ;

reg          sampling;

// UART RX Logic
always @ (posedge rxclk or posedge reset)
if (reset) begin
  rx_reg        <= 0; 
  rx_data       <= 0;
  rx_sample_cnt <= 0;
  rx_cnt        <= 0;
  rx_frame_err  <= 0;
  rx_over_run   <= 0;
  rx_empty      <= 1;
  rx_d1         <= 1;
  rx_d2         <= 1;
  rx_busy       <= 0;
  sampling      <= 0;
end else begin
  // Synchronize the asynch signal
  rx_d1 <= rx_in;
  rx_d2 <= rx_d1;
  // Uload the rx data
  if (uld_rx_data) begin
    rx_data  <= rx_reg;
    rx_empty <= 1;
  end
  // Receive data only when rx is enabled
  if (rx_enable) begin
    // Check if just received start of frame
    if (!rx_busy && !rx_d2) begin
      rx_busy       <= 1;
      rx_sample_cnt <= 1;
      rx_cnt        <= 0;
    end
    // Start of frame detected, Proceed with rest of data
    if (rx_busy) begin
       rx_sample_cnt <= rx_sample_cnt + 1;
       // Logic to sample at middle of data
       if (rx_sample_cnt == 7) begin
          sampling <= 1;
          if ((rx_d2 == 1) && (rx_cnt == 0)) begin
            rx_busy <= 0;
          end else begin
            rx_cnt <= rx_cnt + 1; 
            // Start storing the rx data
            if (rx_cnt > 0 && rx_cnt < 9) begin
              rx_reg[rx_cnt - 1] <= rx_d2;
            end
            if (rx_cnt == 9) begin
               rx_busy <= 0;
               // Check if End of frame received correctly
               if (rx_d2 == 0) begin
                 rx_frame_err <= 1;
               end else begin
                 rx_empty     <= 0;
                 rx_frame_err <= 0;
                 // Check if last rx data was not unloaded,
                 rx_over_run  <= (rx_empty) ? 0 : 1;
               end
            end
          end
       end 
       else begin
         sampling <= 0;
       end
    end 
  end
  if (!rx_enable) begin
    rx_busy <= 0;
  end
end

// UART TX Logic
always @ (posedge txclk or posedge reset)
if (reset) begin
  tx_reg        <= 0;
  tx_empty      <= 1;
  tx_over_run   <= 0;
  tx_out        <= 1;
  tx_cnt        <= 0;
end else begin
   if (ld_tx_data) begin
      if (!tx_empty) begin
        tx_over_run <= 0;
      end else begin
        tx_reg   <= tx_data;
        tx_empty <= 0;
      end
   end
   if (tx_enable && !tx_empty) begin
     tx_cnt <= tx_cnt + 1;
     if (tx_cnt == 0) begin
       tx_out <= 0;
     end
     if (tx_cnt > 0 && tx_cnt < 9) begin
        tx_out <= tx_reg[tx_cnt -1];
     end
     if (tx_cnt == 9) begin
       tx_out <= 1;
       tx_cnt <= 0;
       tx_empty <= 1;
     end
   end
   if (!tx_enable) begin
     tx_cnt <= 0;
   end
end

endmodule

Uart/Alejandro/system.v

// SharkBoad SystemModule
//
// Top Level Design for the Xilinx Spartan 3-100E Device
//---------------------------------------------------------------------------

/*#
# SharkBoad
# Copyright (C) 2012 Bogotá, Colombia
#
# This program is free software: you can redistribute it and/or modify
# it under the terms of the GNU General Public License as published by
# the Free Software Foundation, version 3 of the License.
#
# This program is distributed in the hope that it will be useful,
# but WITHOUT ANY WARRANTY; without even the implied warranty of
# MERCHANTABILITY or FITNESS FOR A PARTICULAR PURPOSE.  See the
# GNU General Public License for more details.
#
# You should have received a copy of the GNU General Public License
# along with this program.  If not, see <http://www.gnu.org/licenses/>.
#*/

module system
#(parameter	clk_freq	= 50000000) 
(
reset          ,
txclk          ,
ld_tx_data     ,
tx_data        ,
tx_enable      ,
tx_out         ,
tx_empty       ,
rxclk          ,
uld_rx_data    ,
rx_data        ,
rx_enable      ,
rx_in          ,
rx_empty
);
// Port declarations
input        reset          ;
input        txclk          ;
input        ld_tx_data     ;
input  [7:0] tx_data        ;
input        tx_enable      ;
output       tx_out         ;
output       tx_empty       ;
input        rxclk          ;
input        uld_rx_data    ;
output [7:0] rx_data        ;
input        rx_enable      ;
input        rx_in          ;
output       rx_empty       ;

/*

wire [31:0] w_ir;// Instructión register
wire [40:0] w_mir;// Vicrocode instruction register
wire [3:0]  w_psr;// Vector que contiene los Condition Codes (flags)
wire [31:0] w_data_mm,// bus que lleva datos de la Main memory al datpath
	    w_bus_a,//Bus A del datapath que sirve como address de la MM
	    w_bus_b;//Bus B del datapath en el que se envian datos a la MM
*/	  

wire tx;
wire empty_uload;

/*Decaración demódulos*/

	//UART a probar 
	uart uart_1(
	.reset(reset)       		   ,
	.txclk(txclk)        	  	   ,
	.ld_tx_data(ld_tx_data)        ,
	.tx_data(tx_data)              ,
	.tx_enable(tx_enable)          ,
	.tx_out(tx)                    ,
	.tx_empty(empty_uload)            ,
	.rxclk(rxclk)          		   ,
	.uld_rx_data(uld_rx_data)      ,
	.rx_data(rx_data)        	   ,
	.rx_enable(rx_enable)          ,
	.rx_in(rx_in)          		   ,
	.rx_empty(rx_empty)
	);

	uart uart_2(
	.reset(reset)       		   ,
	.txclk(txclk)        	  	   ,
	.ld_tx_data(ld_tx_data)        ,
	.tx_data(tx_data)              ,
	.tx_enable(tx_enable)          ,
	.tx_out(tx_out)                ,
	.tx_empty(tx_empty)            ,
	.rxclk(rxclk)          		   ,
	.uld_rx_data(empty_uload)      ,
	.rx_data(rx_data)        	   ,
	.rx_enable(rx_enable)          ,
	.rx_in(tx)          		   ,
	.rx_empty(rx_empty)
	);



endmodule

Uart/Alejandro (cambios)/system_tb.v
//----------------------------------------------------------------------------
//
//----------------------------------------------------------------------------

/*#
# SharkBoad
# Copyright (C) 2012 Bogotá, Colombia
#
# This program is free software: you can redistribute it and/or modify
# it under the terms of the GNU General Public License as published by
# the Free Software Foundation, version 3 of the License.
#
# This program is distributed in the hope that it will be useful,
# but WITHOUT ANY WARRANTY; without even the implied warranty of
# MERCHANTABILITY or FITNESS FOR A PARTICULAR PURPOSE.  See the
# GNU General Public License for more details.
#
# You should have received a copy of the GNU General Public License
# along with this program.  If not, see <http://www.gnu.org/licenses/>.
#*/

`timescale 1 ns / 100 ps

module system_tb;

//----------------------------------------------------------------------------
// Parameter (may differ for physical synthesis)
//----------------------------------------------------------------------------
parameter tck              = 20;       // clock period in ns
parameter clk_freq = 1000000000 / tck; // Frequenzy in HZ
//----------------------------------------------------------------------------
//
//----------------------------------------------------------------------------
reg clk_tb;

reg reset_tb;          
//reg txclk_tb;          
reg ld_tx_data_tb;  
reg [7:0] tx_data_tb;        
reg tx_enable_tb;      
wire tx_out_tb;         
wire tx_empty_tb;       
reg rxclk_tb; 
reg uld_rx_data_tb;
wire [7:0] rx_data_tb;
reg rx_enable_tb;
reg rx_in_tb;     
wire rx_empty_tb;

//----------------------------------------------------------------------------
// Device Under Test 
//----------------------------------------------------------------------------
system #(
	.clk_freq	(	clk_freq	)
) 

dut  (
	.reset(reset_tb)       		   ,
	.txclk(clk_tb)        	  	   ,
	.ld_tx_data(ld_tx_data_tb)        ,
	.tx_data(tx_data_tb)              ,
	.tx_enable(tx_enable_tb)          ,
	.tx_out(tx_out_tb)                ,
	.tx_empty(tx_empty_tb)            ,
	.rxclk(rxclk_tb)          		   ,
	.uld_rx_data(uld_rx_data_tb)      ,
	.rx_data(rx_data_tb)        	   ,
	.rx_enable(rx_enable_tb)          ,
	.rx_in(rx_in_tb)          		   ,
	.rx_empty(rx_empty_tb)
	
);


/* Clocking device */
// Remember this is only for simulation. It never will be syntetizable //
initial begin        
		clk_tb <= 0;
		//txclk_tb <= 0;
		rxclk_tb <= 0;
end

always #(tck*8) clk_tb <= ~clk_tb;
always #(tck/2) rxclk_tb <= ~rxclk_tb;


/* Simulation setup */
initial begin
	//set the file for loggin simulation data
	$dumpfile("system_tb.vcd"); 
	//$monitor("%b,%b,%b",clk_tb,rst_tb,led_tb);
	//export all signals in the simulation viewer
	$dumpvars(-1, dut);
	//$dumpvars(-1,clk_tb,rst_tb,led_tb, dut);
	
	//$dumpvars(-1,clk_tb,rst_tb);
	#0  reset_tb <= 0;
	#0 ld_tx_data_tb <= 0;
	#0 tx_data_tb <= 0;
	#0 tx_enable_tb <= 0;
	#0 uld_rx_data_tb <= 0;
	#0 rx_enable_tb <= 0;
	#0 rx_in_tb <= 1;

	#10

	#0  reset_tb <= 1;
	#0 ld_tx_data_tb <= 0;
	#0 tx_data_tb <= 8'b10101010;
	#0 tx_enable_tb <= 0;
	#0 uld_rx_data_tb <= 0;
	#0 rx_enable_tb <= 0;
	#0 rx_in_tb <= 1;

	#800
	
	#0  reset_tb <= 0;
	#0 ld_tx_data_tb <= 1;
	#0 tx_data_tb <= 8'b10101010;
	#0 tx_enable_tb <= 0;
	#0 uld_rx_data_tb <= 0;
	#0 rx_enable_tb <= 0;
	#0 rx_in_tb <= 1;

	#800
	
	#0  reset_tb <= 0;
	#0 ld_tx_data_tb <= 0;
	#0 tx_data_tb <= 8'b11101111;
	#0 tx_enable_tb <= 1;
	#0 uld_rx_data_tb <= 0;
	#0 rx_enable_tb <= 1;
	#0 rx_in_tb <= 1;

	#5000
	
	#0  reset_tb <= 0;
	#0 ld_tx_data_tb <= 1;
	#0 tx_data_tb <= 8'b11110010;
	#0 tx_enable_tb <= 0;
	#0 uld_rx_data_tb <= 0;
	#0 rx_enable_tb <= 0;
	#0 rx_in_tb <= 1;

	#800
	
	#0  reset_tb <= 0;
	#0 ld_tx_data_tb <= 0;
	#0 tx_data_tb <= 8'b11101111;
	#0 tx_enable_tb <= 1;
	#0 uld_rx_data_tb <= 0;
	#0 rx_enable_tb <= 1;
	#0 rx_in_tb <= 1;

	
	#(tck*5000) $finish;
end
endmodule

Uart/Alejandro/simulation/system_tb.vcd
$date
	Mon Oct  5 18:45:46 2015
$end
$version
	Icarus Verilog
$end
$timescale
	100ps
$end
$scope module system_tb $end
$scope module dut $end
$var wire 1 ! empty_uload $end
$var wire 1 " ld_tx_data $end
$var wire 1 # reset $end
$var wire 8 $ rx_data [7:0] $end
$var wire 1 % rx_empty $end
$var wire 1 & rx_enable $end
$var wire 1 ' rx_in $end
$var wire 1 ( rxclk $end
$var wire 1 ) tx $end
$var wire 8 * tx_data [7:0] $end
$var wire 1 + tx_empty $end
$var wire 1 , tx_enable $end
$var wire 1 - tx_out $end
$var wire 1 . txclk $end
$var wire 1 / uld_rx_data $end
$scope module uart_1 $end
$var wire 1 " ld_tx_data $end
$var wire 1 # reset $end
$var wire 1 & rx_enable $end
$var wire 1 ' rx_in $end
$var wire 1 ( rxclk $end
$var wire 8 0 tx_data [7:0] $end
$var wire 1 , tx_enable $end
$var wire 1 . txclk $end
$var wire 1 / uld_rx_data $end
$var reg 1 1 rx_busy $end
$var reg 4 2 rx_cnt [3:0] $end
$var reg 1 3 rx_d1 $end
$var reg 1 4 rx_d2 $end
$var reg 8 5 rx_data [7:0] $end
$var reg 1 6 rx_empty $end
$var reg 1 7 rx_frame_err $end
$var reg 1 8 rx_over_run $end
$var reg 8 9 rx_reg [7:0] $end
$var reg 4 : rx_sample_cnt [3:0] $end
$var reg 1 ; sampling $end
$var reg 4 < tx_cnt [3:0] $end
$var reg 1 = tx_empty $end
$var reg 1 > tx_out $end
$var reg 1 ? tx_over_run $end
$var reg 8 @ tx_reg [7:0] $end
$upscope $end
$scope module uart_2 $end
$var wire 1 " ld_tx_data $end
$var wire 1 # reset $end
$var wire 1 & rx_enable $end
$var wire 1 ) rx_in $end
$var wire 1 ( rxclk $end
$var wire 8 A tx_data [7:0] $end
$var wire 1 , tx_enable $end
$var wire 1 . txclk $end
$var wire 1 ! uld_rx_data $end
$var reg 1 B rx_busy $end
$var reg 4 C rx_cnt [3:0] $end
$var reg 1 D rx_d1 $end
$var reg 1 E rx_d2 $end
$var reg 8 F rx_data [7:0] $end
$var reg 1 G rx_empty $end
$var reg 1 H rx_frame_err $end
$var reg 1 I rx_over_run $end
$var reg 8 J rx_reg [7:0] $end
$var reg 4 K rx_sample_cnt [3:0] $end
$var reg 1 L sampling $end
$var reg 4 M tx_cnt [3:0] $end
$var reg 1 N tx_empty $end
$var reg 1 O tx_out $end
$var reg 1 P tx_over_run $end
$var reg 8 Q tx_reg [7:0] $end
$upscope $end
$upscope $end
$upscope $end
$enddefinitions $end
#0
$dumpvars
bx Q
xP
xO
xN
bx M
xL
bx K
bx J
xI
xH
xG
bx F
xE
xD
bx C
xB
b0 A
bx @
x?
x>
x=
bx <
x;
bx :
bx 9
x8
x7
x6
bx 5
x4
x3
bx 2
x1
b0 0
0/
0.
x-
0,
x+
b0 *
x)
0(
1'
0&
x%
bx $
0#
0"
x!
$end
#100
b0 <
1>
1)
0?
1=
1!
b0 @
b0 M
1O
1-
0P
1N
1+
b0 Q
0;
01
14
13
16
1%
08
07
b0 2
b0 :
b0 5
b0 $
b0 9
0L
0B
1E
1D
1G
0I
0H
b0 C
b0 K
b0 F
b0 J
b10101010 *
b10101010 0
b10101010 A
1#
1(
#200
0(
#300
1(
#400
0(
#500
1(
#600
0(
#700
1(
#800
0(
#900
1(
#1000
0(
#1100
1(
#1200
0(
#1300
1(
#1400
0(
#1500
1(
#1600
0(
1.
#1700
1(
#1800
0(
#1900
1(
#2000
0(
#2100
1(
#2200
0(
#2300
1(
#2400
0(
#2500
1(
#2600
0(
#2700
1(
#2800
0(
#2900
1(
#3000
0(
#3100
1(
#3200
0(
0.
#3300
1(
#3400
0(
#3500
1(
#3600
0(
#3700
1(
#3800
0(
#3900
1(
#4000
0(
#4100
1(
#4200
0(
#4300
1(
#4400
0(
#4500
1(
#4600
0(
#4700
1(
#4800
0(
1.
#4900
1(
#5000
0(
#5100
1(
#5200
0(
#5300
1(
#5400
0(
#5500
1(
#5600
0(
#5700
1(
#5800
0(
#5900
1(
#6000
0(
#6100
1(
#6200
0(
#6300
1(
#6400
0(
0.
#6500
1(
#6600
0(
#6700
1(
#6800
0(
#6900
1(
#7000
0(
#7100
1(
#7200
0(
#7300
1(
#7400
0(
#7500
1(
#7600
0(
#7700
1(
#7800
0(
#7900
1(
#8000
0(
1.
#8100
1"
0#
1(
#8200
0(
#8300
1(
#8400
0(
#8500
1(
#8600
0(
#8700
1(
#8800
0(
#8900
1(
#9000
0(
#9100
1(
#9200
0(
#9300
1(
#9400
0(
#9500
1(
#9600
0(
0.
#9700
1(
#9800
0(
#9900
1(
#10000
0(
#10100
1(
#10200
0(
#10300
1(
#10400
0(
#10500
1(
#10600
0(
#10700
1(
#10800
0(
#10900
1(
#11000
0(
#11100
1(
#11200
0=
0!
b10101010 @
0N
0+
b10101010 Q
0(
1.
#11300
1(
#11400
0(
#11500
1(
#11600
0(
#11700
1(
#11800
0(
#11900
1(
#12000
0(
#12100
1(
#12200
0(
#12300
1(
#12400
0(
#12500
1(
#12600
0(
#12700
1(
#12800
0(
0.
#12900
1(
#13000
0(
#13100
1(
#13200
0(
#13300
1(
#13400
0(
#13500
1(
#13600
0(
#13700
1(
#13800
0(
#13900
1(
#14000
0(
#14100
1(
#14200
0(
#14300
1(
#14400
0(
1.
#14500
1(
#14600
0(
#14700
1(
#14800
0(
#14900
1(
#15000
0(
#15100
1(
#15200
0(
#15300
1(
#15400
0(
#15500
1(
#15600
0(
#15700
1(
#15800
0(
#15900
1(
#16000
0(
0.
#16100
1&
1,
b11101111 *
b11101111 0
b11101111 A
0"
1(
#16200
0(
#16300
1(
#16400
0(
#16500
1(
#16600
0(
#16700
1(
#16800
0(
#16900
1(
#17000
0(
#17100
1(
#17200
0(
#17300
1(
#17400
0(
#17500
1(
#17600
0>
0)
b1 <
0O
0-
b1 M
0(
1.
#17700
0D
1(
#17800
0(
#17900
0E
1(
#18000
0(
#18100
b1 K
1B
1(
#18200
0(
#18300
b10 K
1(
#18400
0(
#18500
b11 K
1(
#18600
0(
#18700
b100 K
1(
#18800
0(
#18900
b101 K
1(
#19000
0(
#19100
b110 K
1(
#19200
0(
0.
#19300
b111 K
1(
#19400
0(
#19500
b1 C
1L
b1000 K
1(
#19600
0(
#19700
0L
b1001 K
1(
#19800
0(
#19900
b1010 K
1(
#20000
0(
#20100
b1011 K
1(
#20200
0(
#20300
b1100 K
1(
#20400
0(
#20500
b1101 K
1(
#20600
0(
#20700
b1110 K
1(
#20800
b10 M
b10 <
0(
1.
#20900
b1111 K
1(
#21000
0(
#21100
b0 K
1(
#21200
0(
#21300
b1 K
1(
#21400
0(
#21500
b10 K
1(
#21600
0(
#21700
b11 K
1(
#21800
0(
#21900
b100 K
1(
#22000
0(
#22100
b101 K
1(
#22200
0(
#22300
b110 K
1(
#22400
0(
0.
#22500
b111 K
1(
#22600
0(
#22700
b0 J
b10 C
1L
b1000 K
1(
#22800
0(
#22900
0L
b1001 K
1(
#23000
0(
#23100
b1010 K
1(
#23200
0(
#23300
b1011 K
1(
#23400
0(
#23500
b1100 K
1(
#23600
0(
#23700
b1101 K
1(
#23800
0(
#23900
b1110 K
1(
#24000
1>
1)
b11 <
1O
1-
b11 M
0(
1.
#24100
b1111 K
1D
1(
#24200
0(
#24300
b0 K
1E
1(
#24400
0(
#24500
b1 K
1(
#24600
0(
#24700
b10 K
1(
#24800
0(
#24900
b11 K
1(
#25000
0(
#25100
b100 K
1(
#25200
0(
#25300
b101 K
1(
#25400
0(
#25500
b110 K
1(
#25600
0(
0.
#25700
b111 K
1(
#25800
0(
#25900
b10 J
b11 C
1L
b1000 K
1(
#26000
0(
#26100
0L
b1001 K
1(
#26200
0(
#26300
b1010 K
1(
#26400
0(
#26500
b1011 K
1(
#26600
0(
#26700
b1100 K
1(
#26800
0(
#26900
b1101 K
1(
#27000
0(
#27100
b1110 K
1(
#27200
0O
0-
b100 M
0>
0)
b100 <
0(
1.
#27300
b1111 K
0D
1(
#27400
0(
#27500
b0 K
0E
1(
#27600
0(
#27700
b1 K
1(
#27800
0(
#27900
b10 K
1(
#28000
0(
#28100
b11 K
1(
#28200
0(
#28300
b100 K
1(
#28400
0(
#28500
b101 K
1(
#28600
0(
#28700
b110 K
1(
#28800
0(
0.
#28900
b111 K
1(
#29000
0(
#29100
b10 J
b100 C
1L
b1000 K
1(
#29200
0(
#29300
0L
b1001 K
1(
#29400
0(
#29500
b1010 K
1(
#29600
0(
#29700
b1011 K
1(
#29800
0(
#29900
b1100 K
1(
#30000
0(
#30100
b1101 K
1(
#30200
0(
#30300
b1110 K
1(
#30400
1>
1)
b101 <
1O
1-
b101 M
0(
1.
#30500
b1111 K
1D
1(
#30600
0(
#30700
b0 K
1E
1(
#30800
0(
#30900
b1 K
1(
#31000
0(
#31100
b10 K
1(
#31200
0(
#31300
b11 K
1(
#31400
0(
#31500
b100 K
1(
#31600
0(
#31700
b101 K
1(
#31800
0(
#31900
b110 K
1(
#32000
0(
0.
#32100
b111 K
1(
#32200
0(
#32300
b1010 J
b101 C
1L
b1000 K
1(
#32400
0(
#32500
0L
b1001 K
1(
#32600
0(
#32700
b1010 K
1(
#32800
0(
#32900
b1011 K
1(
#33000
0(
#33100
b1100 K
1(
#33200
0(
#33300
b1101 K
1(
#33400
0(
#33500
b1110 K
1(
#33600
0O
0-
b110 M
0>
0)
b110 <
0(
1.
#33700
b1111 K
0D
1(
#33800
0(
#33900
b0 K
0E
1(
#34000
0(
#34100
b1 K
1(
#34200
0(
#34300
b10 K
1(
#34400
0(
#34500
b11 K
1(
#34600
0(
#34700
b100 K
1(
#34800
0(
#34900
b101 K
1(
#35000
0(
#35100
b110 K
1(
#35200
0(
0.
#35300
b111 K
1(
#35400
0(
#35500
b1010 J
b110 C
1L
b1000 K
1(
#35600
0(
#35700
0L
b1001 K
1(
#35800
0(
#35900
b1010 K
1(
#36000
0(
#36100
b1011 K
1(
#36200
0(
#36300
b1100 K
1(
#36400
0(
#36500
b1101 K
1(
#36600
0(
#36700
b1110 K
1(
#36800
1>
1)
b111 <
1O
1-
b111 M
0(
1.
#36900
b1111 K
1D
1(
#37000
0(
#37100
b0 K
1E
1(
#37200
0(
#37300
b1 K
1(
#37400
0(
#37500
b10 K
1(
#37600
0(
#37700
b11 K
1(
#37800
0(
#37900
b100 K
1(
#38000
0(
#38100
b101 K
1(
#38200
0(
#38300
b110 K
1(
#38400
0(
0.
#38500
b111 K
1(
#38600
0(
#38700
b101010 J
b111 C
1L
b1000 K
1(
#38800
0(
#38900
0L
b1001 K
1(
#39000
0(
#39100
b1010 K
1(
#39200
0(
#39300
b1011 K
1(
#39400
0(
#39500
b1100 K
1(
#39600
0(
#39700
b1101 K
1(
#39800
0(
#39900
b1110 K
1(
#40000
0O
0-
b1000 M
0>
0)
b1000 <
0(
1.
#40100
b1111 K
0D
1(
#40200
0(
#40300
b0 K
0E
1(
#40400
0(
#40500
b1 K
1(
#40600
0(
#40700
b10 K
1(
#40800
0(
#40900
b11 K
1(
#41000
0(
#41100
b100 K
1(
#41200
0(
#41300
b101 K
1(
#41400
0(
#41500
b110 K
1(
#41600
0(
0.
#41700
b111 K
1(
#41800
0(
#41900
b101010 J
b1000 C
1L
b1000 K
1(
#42000
0(
#42100
0L
b1001 K
1(
#42200
0(
#42300
b1010 K
1(
#42400
0(
#42500
b1011 K
1(
#42600
0(
#42700
b1100 K
1(
#42800
0(
#42900
b1101 K
1(
#43000
0(
#43100
b1110 K
1(
#43200
1>
1)
b1001 <
1O
1-
b1001 M
0(
1.
#43300
b1111 K
1D
1(
#43400
0(
#43500
b0 K
1E
1(
#43600
0(
#43700
b1 K
1(
#43800
0(
#43900
b10 K
1(
#44000
0(
#44100
b11 K
1(
#44200
0(
#44300
b100 K
1(
#44400
0(
#44500
b101 K
1(
#44600
0(
#44700
b110 K
1(
#44800
0(
0.
#44900
b111 K
1(
#45000
0(
#45100
b10101010 J
b1001 C
1L
b1000 K
1(
#45200
0(
#45300
0L
b1001 K
1(
#45400
0(
#45500
b1010 K
1(
#45600
0(
#45700
b1011 K
1(
#45800
0(
#45900
b1100 K
1(
#46000
0(
#46100
b1101 K
1(
#46200
0(
#46300
b1110 K
1(
#46400
1N
1+
b0 M
1=
1!
b0 <
0(
1.
#46500
b1111 K
b10101010 F
bx0x0x0x0 $
1(
#46600
0(
#46700
b0 K
1(
#46800
0(
#46900
b1 K
1(
#47000
0(
#47100
b10 K
1(
#47200
0(
#47300
b11 K
1(
#47400
0(
#47500
b100 K
1(
#47600
0(
#47700
b101 K
1(
#47800
0(
#47900
b110 K
1(
#48000
0(
0.
#48100
b111 K
1(
#48200
0(
#48300
0G
x%
0B
b1010 C
1L
b1000 K
1(
#48400
0(
#48500
1G
1%
1(
